modules/A0.py
modules/A1.py
modules/A2.py
modules/A3.py
modules/__init__.py
modules/dice.py
modules/k_let.py
modules/mono.py
Lino_Boehler_A5-0.1.0.dist-info/METADATA
Lino_Boehler_A5-0.1.0.dist-info/WHEEL
Lino_Boehler_A5-0.1.0.dist-info/top_level.txt
Lino_Boehler_A5-0.1.0.dist-info/RECORD
