Metadata-Version: 2.1
Name: Lino-Boehler-A5
Version: 0.1.0
Summary: First Package include all Exercises so far
Home-page: UNKNOWN
Author: Lino Boehler
Author-email: lino.boehler@gmx.net
License: MIT-License
Platform: UNKNOWN
Requires-Dist: numpy
